Metadata-Version: 1.1
Name: python-testdata
Version: 1.0.5
Summary: A small package that helps generate content to fill databases for tests.
Home-page: http://github.com/arieb/python-testdata
Author: Arie Bro
Author-email: ariebro@gmail.com
License: MIT
Keywords: factory testing test unittest mongo data testdata database json elasticsearch
Platform: UNKNOWN
Classifier: Intended Audience :: Developers
Classifier: Topic :: Software Development :: Testing
Classifier: License :: OSI Approved :: MIT License
